nfd2c/__init__.py
nfd2c/__main__.py
nfd2c/nfd2c.py
unicode_nfd2c-1.0.2.dist-info/LICENSE
unicode_nfd2c-1.0.2.dist-info/METADATA
unicode_nfd2c-1.0.2.dist-info/WHEEL
unicode_nfd2c-1.0.2.dist-info/entry_points.txt
unicode_nfd2c-1.0.2.dist-info/top_level.txt
unicode_nfd2c-1.0.2.dist-info/RECORD
