Metadata-Version: 2.1
Name: unicode-nfd2c
Version: 1.0.2
Summary: Renames NFD Unicode names to NFC
Home-page: https://github.com/xvim64/nfd2c
Author: xvim64
Author-email: xvim64@gmail.com
License: GPLv2
Keywords: mac,hangeul,hangul,unicode,nfd,nfc
Platform: UNKNOWN
Classifier: Environment :: Console
Classifier: Programming Language :: Python :: 3
Classifier: License :: OSI Approved :: GNU General Public License v2 (GPLv2)
Classifier: Operating System :: OS Independent
Requires-Python: >=3
License-File: LICENSE
